libpythonpro/__init__.py
libpythonpro/github_api.py
libpythonpro/spam/__init__.py
libpythonpro/spam/db.py
libpythonpro/spam/enviador_de_email.py
libpythonpro/spam/main.py
libpythonpro/spam/modelos.py
libpythonpro/tests/__init__.py
libpythonpro/tests/test_exemplo.py
libpythonpro/tests/test_spam/__init__.py
libpythonpro/tests/test_spam/conftest.py
libpythonpro/tests/test_spam/test_enviador_de_email.py
libpythonpro/tests/test_spam/test_envio_para_base_de_usuarios.py
libpythonpro/tests/test_spam/test_github_api.py
libpythonpro/tests/test_spam/test_usuarios.py
libpythonprobruno-0.9.dist-info/LICENSE
libpythonprobruno-0.9.dist-info/METADATA
libpythonprobruno-0.9.dist-info/WHEEL
libpythonprobruno-0.9.dist-info/top_level.txt
libpythonprobruno-0.9.dist-info/RECORD
