Metadata-Version: 2.1
Name: libpythonprobruno
Version: 0.9
Summary: Módulo para exemplificar construção de projetos Python no curso PyTools
Home-page: https://github.com/brjatoba92/libpythonprobr
Author: Bruno Jatobá
Author-email: brjatoba92@gmail.com
License: GNU AFFERO GENERAL PUBLIC LICENSE
Platform: UNKNOWN
Classifier: Development Status :: 2 - Pre-Alpha
Classifier: Environment :: Console
Classifier: Intended Audience :: Developers
Classifier: License :: OSI Approved :: GNU Affero General Public License v3 or later (AGPLv3+)
Classifier: Operating System :: OS Independent
Classifier: Programming Language :: Python
Classifier: Programming Language :: Python :: 3.8
Classifier: Framework :: Pytest
Requires-Dist: requests
